complubot/__init__.py
complubot/libreria_dodo.py
libreria_dodo-0.0.8.dist-info/LICENSE
libreria_dodo-0.0.8.dist-info/METADATA
libreria_dodo-0.0.8.dist-info/WHEEL
libreria_dodo-0.0.8.dist-info/top_level.txt
libreria_dodo-0.0.8.dist-info/RECORD
