Metadata-Version: 2.1
Name: libreria dodo
Version: 0.0.8
Summary: Libreria para la placa dodo y dodo lite
Home-page: https://github.com/Complubot/Libreria-dodo
Author: Complubot
Author-email: info@complubot.com
License: UNKNOWN
Project-URL: Bug Tracker, https://github.com/Complubot/Libreria-dodo/issues
Platform: UNKNOWN
Classifier: Programming Language :: Python :: Implementation :: MicroPython
Classifier: License :: OSI Approved :: MIT License
Classifier: Operating System :: OS Independent
Requires-Python: >=3.6
License-File: LICENSE
